dune_analytics/__init__.py
dune_analytics-0.0.1.dist-info/LICENSE
dune_analytics-0.0.1.dist-info/METADATA
dune_analytics-0.0.1.dist-info/WHEEL
dune_analytics-0.0.1.dist-info/top_level.txt
dune_analytics-0.0.1.dist-info/RECORD
